html_table_extractor/__init__.py
html_table_extractor/extractor.py
html_table_extractor-1.4.0.dist-info/LICENSE
html_table_extractor-1.4.0.dist-info/METADATA
html_table_extractor-1.4.0.dist-info/WHEEL
html_table_extractor-1.4.0.dist-info/top_level.txt
html_table_extractor-1.4.0.dist-info/RECORD
