Metadata-Version: 2.1
Name: html-table-extractor
Version: 1.4.0
Summary: A python library for extracting data from html table
Home-page: https://github.com/yuanxu-li/html-table-extractor
Author: Justin Li
Author-email: yuanxu.lee@gmail.com
License: MIT
Keywords: html table beautifulsoup crawler scrape
Platform: UNKNOWN
Classifier: Development Status :: 3 - Alpha
Classifier: Intended Audience :: Developers
Classifier: License :: OSI Approved :: MIT License
Classifier: Programming Language :: Python :: 2
Classifier: Programming Language :: Python :: 2.7
Classifier: Programming Language :: Python :: 3
Classifier: Programming Language :: Python :: 3.5
Requires-Dist: beautifulsoup4 (==4.5.3)
